spring_clean_app/__init__.py
spring_clean_app/actions/__init__.py
spring_clean_app/actions/boilerplate/__init__.py
spring_clean_app/actions/boilerplate/core/__init__.py
spring_clean_app/actions/boilerplate/core/app_usecase.py
spring_clean_app/actions/boilerplate/core/core_domain.py
spring_clean_app/actions/boilerplate/core/core_exception.py
spring_clean_app/actions/boilerplate/core/core_utils.py
spring_clean_app/actions/boilerplate/core/usecase_config.py
spring_clean_app/actions/boilerplate/dependencies_config.py
spring_clean_app/actions/boilerplate/entry_point_config.py
spring_clean_app/actions/boilerplate/infra/client/__init__.py
spring_clean_app/actions/boilerplate/infra/client/client_placeholder.py
spring_clean_app/actions/boilerplate/infra/data/__init__.py
spring_clean_app/actions/boilerplate/infra/data/data_entities.py
spring_clean_app/actions/boilerplate/infra/data/data_mapper.py
spring_clean_app/actions/boilerplate/infra/data/data_repositories.py
spring_clean_app/actions/boilerplate/presenter/rest/rest_common.py
spring_clean_app/actions/boilerplate/presenter/rest/rest_controller.py
spring_clean_app/actions/boilerplate/presenter/web_config.py
spring_clean_app/actions/boilerplate/resources/migration.py
spring_clean_app/actions/boilerplate/resources/profile_config.py
spring_clean_app/actions/download_project.py
spring_clean_app/actions/project_structure.py
spring_clean_app/main.py
spring_clean_app/utils/__init__.py
spring_clean_app/utils/prompts.py
spring_clean_app/utils/utils.py
spring_clean_app/utils/validators.py
spring_clean_app-1.0.0.dist-info/METADATA
spring_clean_app-1.0.0.dist-info/WHEEL
spring_clean_app-1.0.0.dist-info/entry_points.txt
spring_clean_app-1.0.0.dist-info/RECORD
